<?xml version="1.0" encoding="utf-8"?>
<ArrayOfEngineer xmlns:xsi="http://www.w3.org/2001/XMLSchema-instance" xmlns:xsd="http://www.w3.org/2001/XMLSchema">
  <Engineer>
    <Id>310479376</Id>
    <Name>Dani Levi</Name>
    <Email>Dani Levi310479376@gmail.com</Email>
    <Cost>300</Cost>
    <Level>AdvancedBeginner</Level>
    <Active>true</Active>
  </Engineer>
  <Engineer>
    <Id>317726415</Id>
    <Name>Eli Amar</Name>
    <Email>Eli Amar317726415@gmail.com</Email>
    <Cost>400</Cost>
    <Level>Beginner</Level>
    <Active>true</Active>
  </Engineer>
  <Engineer>
    <Id>327380762</Id>
    <Name>Yair Cohen</Name>
    <Email>Yair Cohen327380762@gmail.com</Email>
    <Cost>200</Cost>
    <Level>Competent</Level>
    <Active>true</Active>
  </Engineer>
  <Engineer>
    <Id>264868405</Id>
    <Name>Ariela Levin</Name>
    <Email>Ariela Levin264868405@gmail.com</Email>
    <Cost>300</Cost>
    <Level>AdvancedBeginner</Level>
    <Active>true</Active>
  </Engineer>
  <Engineer>
    <Id>227851498</Id>
    <Name>Dina Klein</Name>
    <Email>Dina Klein227851498@gmail.com</Email>
    <Cost>200</Cost>
    <Level>Competent</Level>
    <Active>true</Active>
  </Engineer>
  <Engineer>
    <Id>218619435</Id>
    <Name>Shira Israelof</Name>
    <Email>Shira Israelof218619435@gmail.com</Email>
    <Cost>200</Cost>
    <Level>Expert</Level>
    <Active>true</Active>
  </Engineer>
  <Engineer>
    <Id>284963730</Id>
    <Name>Sarale taharani</Name>
    <Email>Sarale taharani284963730@gmail.com</Email>
    <Cost>200</Cost>
    <Level>Expert</Level>
    <Active>true</Active>
  </Engineer>
  <Engineer>
    <Id>266467742</Id>
    <Name>Hodaya Shteinhouse</Name>
    <Email>Hodaya Shteinhouse266467742@gmail.com</Email>
    <Cost>200</Cost>
    <Level>Expert</Level>
    <Active>true</Active>
  </Engineer>
  <Engineer>
    <Id>394131817</Id>
    <Name>Hadassa Bradpiece</Name>
    <Email>Hadassa Bradpiece394131817@gmail.com</Email>
    <Cost>200</Cost>
    <Level>Proficient</Level>
    <Active>true</Active>
  </Engineer>
  <Engineer>
    <Id>338641527</Id>
    <Name>Noa Marciano</Name>
    <Email>Noa Marciano338641527@gmail.com</Email>
    <Cost>400</Cost>
    <Level>Beginner</Level>
    <Active>true</Active>
  </Engineer>
  <Engineer>
    <Id>313968367</Id>
    <Name>Yossi Cohen</Name>
    <Email>Yossi Cohen313968367@gmail.com</Email>
    <Cost>200</Cost>
    <Level>Proficient</Level>
    <Active>true</Active>
  </Engineer>
  <Engineer>
    <Id>391010537</Id>
    <Name>Shifra Weiss</Name>
    <Email>Shifra Weiss391010537@gmail.com</Email>
    <Cost>400</Cost>
    <Level>Beginner</Level>
    <Active>true</Active>
  </Engineer>
  <Engineer>
    <Id>283578610</Id>
    <Name>Dina Bradpiece</Name>
    <Email>Dina Bradpiece283578610@gmail.com</Email>
    <Cost>200</Cost>
    <Level>Expert</Level>
    <Active>true</Active>
  </Engineer>
  <Engineer>
    <Id>303796067</Id>
    <Name>Tamar Levi</Name>
    <Email>Tamar Levi303796067@gmail.com</Email>
    <Cost>200</Cost>
    <Level>Expert</Level>
    <Active>true</Active>
  </Engineer>
</ArrayOfEngineer>